cicd/__init__.py
cicd/createFitNesseArtifact.py
cicd/createFolder.py
cicd/createGroup.py
cicd/createInformaticaPlatformApp.py
cicd/createInformaticaPlatformArtifact.py
cicd/createOracleArtifact.py
cicd/createProject.py
cicd/createSchedulerArtifact.py
cicd/createUser.py
cicd/deleteFolder.py
cicd/deleteGroup.py
cicd/deleteProject.py
cicd/deleteUser.py
cicd/deployInformaticaPlatformApp.py
cicd/deployInformaticaPlatformArtifact.py
cicd/deployOracle.py
cicd/deploySchedulerArtifact.py
cicd/exportConnections.py
cicd/exportUsersAndGroups.py
cicd/importConnections.py
cicd/importUsersAndGroups.py
cicd/listConnectionOptions.py
cicd/listConnections.py
cicd/database/__init__.py
cicd/database/artifact.py
cicd/database/databaseArtifactChecks.py
cicd/database/dbConstants.py
cicd/database/dbSettings.py
cicd/database/utilities/OracleUtils.py
cicd/database/utilities/__init__.py
cicd/fitnesse/__init__.py
cicd/fitnesse/artifact.py
cicd/fitnesse/fitnesseArtifactChecks.py
cicd/fitnesse/fitnesseConstants.py
cicd/fitnesse/fitnesseSettings.py
cicd/informatica/__init__.py
cicd/informatica/artifact.py
cicd/informatica/buildCommand.py
cicd/informatica/executeInfacmd.py
cicd/informatica/infaAppChecks.py
cicd/informatica/infaArtifactChecks.py
cicd/informatica/infaConstants.py
cicd/informatica/infaSettings.py
cicd/informatica/jobManagement.py
cicd/informatica/manageConnection.py
cicd/informatica/manageFolder.py
cicd/informatica/manageSecurity.py
cicd/informatica/manageWorkflow.py
cicd/informatica/application/__init__.py
cicd/informatica/application/artifact.py
cicd/informatica/application/listApplication.py
cicd/scheduler/__init__.py
cicd/scheduler/artifact.py
cicd/scheduler/schedulerArtifactChecks.py
cicd/scheduler/schedulerConstants.py
cicd/scheduler/schedulerSettings.py
execution/__init__.py
execution/runMapping.py
execution/runProfile.py
execution/runScorecard.py
execution/runWorkflow.py
supporting/__init__.py
supporting/artifactHandling.py
supporting/deploylist.py
supporting/encryption.py
devops_informatica_tools-1.2.26.dist-info/LICENSE
devops_informatica_tools-1.2.26.dist-info/METADATA
devops_informatica_tools-1.2.26.dist-info/WHEEL
devops_informatica_tools-1.2.26.dist-info/top_level.txt
devops_informatica_tools-1.2.26.dist-info/RECORD
