Metadata-Version: 2.1
Name: devops-informatica-tools
Version: 1.2.26
Summary: DevOps and CI-CD Pipeline scripts for Informatica Platform related projects
Home-page: https://github.com/consag/devops-informatica-tools
Author: Jac. Beekers
Author-email: jactools@consag.nl
License: UNKNOWN
Platform: UNKNOWN
Classifier: Programming Language :: Python :: 3
Classifier: License :: OSI Approved :: MIT License
Classifier: Operating System :: OS Independent
Requires-Python: >=3.6
